<annotation>
	<folder>Bags</folder>
	<filename>bagz154.jpg</filename>
	<path>C:\Users\Rod\Pictures\Trash\Resized_800_600\Bags Resized\Bags\bagz154.jpg</path>
	<source>
		<database>Unknown</database>
	</source>
	<size>
		<width>600</width>
		<height>800</height>
		<depth>3</depth>
	</size>
	<segmented>0</segmented>
	<object>
		<name>bag</name>
		<pose>Unspecified</pose>
		<truncated>0</truncated>
		<difficult>0</difficult>
		<bndbox>
			<xmin>143</xmin>
			<ymin>347</ymin>
			<xmax>263</xmax>
			<ymax>444</ymax>
		</bndbox>
	</object>
	<object>
		<name>bag</name>
		<pose>Unspecified</pose>
		<truncated>1</truncated>
		<difficult>0</difficult>
		<bndbox>
			<xmin>1</xmin>
			<ymin>229</ymin>
			<xmax>84</xmax>
			<ymax>287</ymax>
		</bndbox>
	</object>
	<object>
		<name>bag</name>
		<pose>Unspecified</pose>
		<truncated>0</truncated>
		<difficult>0</difficult>
		<bndbox>
			<xmin>293</xmin>
			<ymin>535</ymin>
			<xmax>454</xmax>
			<ymax>664</ymax>
		</bndbox>
	</object>
	<object>
		<name>bag</name>
		<pose>Unspecified</pose>
		<truncated>1</truncated>
		<difficult>0</difficult>
		<bndbox>
			<xmin>538</xmin>
			<ymin>269</ymin>
			<xmax>600</xmax>
			<ymax>331</ymax>
		</bndbox>
	</object>
	<object>
		<name>bag</name>
		<pose>Unspecified</pose>
		<truncated>0</truncated>
		<difficult>0</difficult>
		<bndbox>
			<xmin>497</xmin>
			<ymin>194</ymin>
			<xmax>585</xmax>
			<ymax>235</ymax>
		</bndbox>
	</object>
	<object>
		<name>bag</name>
		<pose>Unspecified</pose>
		<truncated>0</truncated>
		<difficult>0</difficult>
		<bndbox>
			<xmin>215</xmin>
			<ymin>198</ymin>
			<xmax>314</xmax>
			<ymax>249</ymax>
		</bndbox>
	</object>
	<object>
		<name>bottle</name>
		<pose>Unspecified</pose>
		<truncated>0</truncated>
		<difficult>0</difficult>
		<bndbox>
			<xmin>424</xmin>
			<ymin>44</ymin>
			<xmax>448</xmax>
			<ymax>80</ymax>
		</bndbox>
	</object>
</annotation>
