<annotation>
	<folder>Bags</folder>
	<filename>bagz139.jpg</filename>
	<path>C:\Users\Rod\Pictures\Trash\Resized_800_600\Bags Resized\Bags\bagz139.jpg</path>
	<source>
		<database>Unknown</database>
	</source>
	<size>
		<width>600</width>
		<height>800</height>
		<depth>3</depth>
	</size>
	<segmented>0</segmented>
	<object>
		<name>bag</name>
		<pose>Unspecified</pose>
		<truncated>0</truncated>
		<difficult>0</difficult>
		<bndbox>
			<xmin>121</xmin>
			<ymin>223</ymin>
			<xmax>221</xmax>
			<ymax>271</ymax>
		</bndbox>
	</object>
	<object>
		<name>bag</name>
		<pose>Unspecified</pose>
		<truncated>0</truncated>
		<difficult>0</difficult>
		<bndbox>
			<xmin>263</xmin>
			<ymin>343</ymin>
			<xmax>382</xmax>
			<ymax>438</ymax>
		</bndbox>
	</object>
	<object>
		<name>bag</name>
		<pose>Unspecified</pose>
		<truncated>0</truncated>
		<difficult>0</difficult>
		<bndbox>
			<xmin>402</xmin>
			<ymin>543</ymin>
			<xmax>565</xmax>
			<ymax>688</ymax>
		</bndbox>
	</object>
	<object>
		<name>bag</name>
		<pose>Unspecified</pose>
		<truncated>1</truncated>
		<difficult>0</difficult>
		<bndbox>
			<xmin>1</xmin>
			<ymin>594</ymin>
			<xmax>52</xmax>
			<ymax>787</ymax>
		</bndbox>
	</object>
	<object>
		<name>bag</name>
		<pose>Unspecified</pose>
		<truncated>0</truncated>
		<difficult>0</difficult>
		<bndbox>
			<xmin>346</xmin>
			<ymin>203</ymin>
			<xmax>441</xmax>
			<ymax>249</ymax>
		</bndbox>
	</object>
	<object>
		<name>bottle</name>
		<pose>Unspecified</pose>
		<truncated>0</truncated>
		<difficult>0</difficult>
		<bndbox>
			<xmin>568</xmin>
			<ymin>54</ymin>
			<xmax>594</xmax>
			<ymax>87</ymax>
		</bndbox>
	</object>
</annotation>
