<annotation>
	<folder>OldNewCans</folder>
	<filename>cans131.jpg</filename>
	<path>C:\Users\Rod\Pictures\Trash\Resized_800_600\Cans Resized\OldNewCans\cans131.jpg</path>
	<source>
		<database>Unknown</database>
	</source>
	<size>
		<width>600</width>
		<height>800</height>
		<depth>3</depth>
	</size>
	<segmented>0</segmented>
	<object>
		<name>can</name>
		<pose>Unspecified</pose>
		<truncated>0</truncated>
		<difficult>0</difficult>
		<bndbox>
			<xmin>72</xmin>
			<ymin>451</ymin>
			<xmax>141</xmax>
			<ymax>515</ymax>
		</bndbox>
	</object>
	<object>
		<name>can</name>
		<pose>Unspecified</pose>
		<truncated>0</truncated>
		<difficult>0</difficult>
		<bndbox>
			<xmin>156</xmin>
			<ymin>311</ymin>
			<xmax>191</xmax>
			<ymax>346</ymax>
		</bndbox>
	</object>
	<object>
		<name>can</name>
		<pose>Unspecified</pose>
		<truncated>0</truncated>
		<difficult>0</difficult>
		<bndbox>
			<xmin>275</xmin>
			<ymin>364</ymin>
			<xmax>344</xmax>
			<ymax>397</ymax>
		</bndbox>
	</object>
	<object>
		<name>can</name>
		<pose>Unspecified</pose>
		<truncated>0</truncated>
		<difficult>0</difficult>
		<bndbox>
			<xmin>455</xmin>
			<ymin>399</ymin>
			<xmax>505</xmax>
			<ymax>450</ymax>
		</bndbox>
	</object>
	<object>
		<name>can</name>
		<pose>Unspecified</pose>
		<truncated>0</truncated>
		<difficult>0</difficult>
		<bndbox>
			<xmin>332</xmin>
			<ymin>543</ymin>
			<xmax>428</xmax>
			<ymax>627</ymax>
		</bndbox>
	</object>
</annotation>
