<annotation>
	<folder>Resized New Mix</folder>
	<filename>mix81.jpg</filename>
	<path>C:\Users\Rod\Pictures\Trash\Resized_800_600\Resized New Mix\mix81.jpg</path>
	<source>
		<database>Unknown</database>
	</source>
	<size>
		<width>600</width>
		<height>800</height>
		<depth>3</depth>
	</size>
	<segmented>0</segmented>
	<object>
		<name>plate</name>
		<pose>Unspecified</pose>
		<truncated>0</truncated>
		<difficult>0</difficult>
		<bndbox>
			<xmin>286</xmin>
			<ymin>335</ymin>
			<xmax>386</xmax>
			<ymax>401</ymax>
		</bndbox>
	</object>
	<object>
		<name>plate</name>
		<pose>Unspecified</pose>
		<truncated>1</truncated>
		<difficult>0</difficult>
		<bndbox>
			<xmin>521</xmin>
			<ymin>469</ymin>
			<xmax>600</xmax>
			<ymax>554</ymax>
		</bndbox>
	</object>
	<object>
		<name>can</name>
		<pose>Unspecified</pose>
		<truncated>1</truncated>
		<difficult>0</difficult>
		<bndbox>
			<xmin>407</xmin>
			<ymin>692</ymin>
			<xmax>534</xmax>
			<ymax>800</ymax>
		</bndbox>
	</object>
	<object>
		<name>can</name>
		<pose>Unspecified</pose>
		<truncated>0</truncated>
		<difficult>0</difficult>
		<bndbox>
			<xmin>116</xmin>
			<ymin>476</ymin>
			<xmax>215</xmax>
			<ymax>525</ymax>
		</bndbox>
	</object>
</annotation>
